[{"has_filesystem":true,"diskio":{},"has_network":true,"memory":{"failcnt":0,"container_data":{"pgmajfault":0,"pgfault":1154},"cache":0,"rss":2088960,"swap":0,"usage":2801664,"hierarchical_data":{"pgmajfault":0,"pgfault":1154},"working_set":2801664},"cpu":{"cfs":{"throttled_time":0,"periods":0,"throttled_periods":0},"load_average":0,"usage":{"per_cpu_usage":[15400184,3441090],"total":18841274,"system":0,"user":10000000}},"has_load":false,"has_cpu":true,"network":{"tcp":{"SynSent":0,"Established":0,"SynRecv":0,"Close":0,"LastAck":0,"Listen":0,"TimeWait":0,"Closing":0,"FinWait1":0,"CloseWait":0,"FinWait2":0},"interfaces":[{"tx_packets":0,"tx_errors":0,"tx_dropped":0,"rx_dropped":0,"name":"ip6gre0","rx_bytes":0,"tx_bytes":0,"rx_packets":0,"rx_errors":0},{"tx_packets":0,"tx_errors":0,"tx_dropped":0,"rx_dropped":0,"name":"tunl0","rx_bytes":0,"tx_bytes":0,"rx_packets":0,"rx_errors":0},{"tx_packets":0,"tx_errors":0,"tx_dropped":0,"rx_dropped":0,"name":"ip6_vti0","rx_bytes":0,"tx_bytes":0,"rx_packets":0,"rx_errors":0},{"tx_packets":0,"tx_errors":0,"tx_dropped":0,"rx_dropped":0,"name":"sit0","rx_bytes":0,"tx_bytes":0,"rx_packets":0,"rx_errors":0},{"tx_packets":0,"tx_errors":0,"tx_dropped":0,"rx_dropped":0,"name":"eth0","rx_bytes":90,"tx_bytes":0,"rx_packets":1,"rx_errors":0},{"tx_packets":0,"tx_errors":0,"tx_dropped":0,"rx_dropped":0,"name":"ip_vti0","rx_bytes":0,"tx_bytes":0,"rx_packets":0,"rx_errors":0},{"tx_packets":0,"tx_errors":0,"tx_dropped":0,"rx_dropped":0,"name":"gretap0","rx_bytes":0,"tx_bytes":0,"rx_packets":0,"rx_errors":0},{"tx_packets":0,"tx_errors":0,"tx_dropped":0,"rx_dropped":0,"name":"gre0","rx_bytes":0,"tx_bytes":0,"rx_packets":0,"rx_errors":0},{"tx_packets":0,"tx_errors":0,"tx_dropped":0,"rx_dropped":0,"name":"ip6tnl0","rx_bytes":0,"tx_bytes":0,"rx_packets":0,"rx_errors":0}],"tcp6":{"SynSent":0,"Established":0,"SynRecv":0,"Close":0,"LastAck":0,"Listen":0,"TimeWait":0,"Closing":0,"FinWait1":0,"CloseWait":0,"FinWait2":0}},"has_diskio":true,"load_stats":{"nr_io_wait":0,"nr_running":0,"nr_uninterruptible":0,"nr_sleeping":0,"nr_stopped":0},"has_custom_metrics":false,"has_memory":true,"timestamp":"2017-08-11T05:48:55.714842294Z"}
]